qb_quasar/__init__.py
qb_quasar/__main__.py
qb_quasar/building/__init__.py
qb_quasar/building/build_tools.py
qb_quasar/building/compiling.py
qb_quasar/building/runner.py
qb_quasar/helpers.py
qb_quasar/initializing.py
qb_quasar/managing/__init__.py
qb_quasar/managing/filegenerator.py
qb_quasar/managing/installing.py
qb_quasar/packaging/__init__.py
qb_quasar/packaging/packager.py
qb_quasar/packaging/publisher.py
qb_quasar-0.1.4.dist-info/entry_points.txt
qb_quasar-0.1.4.dist-info/METADATA
qb_quasar-0.1.4.dist-info/WHEEL
qb_quasar-0.1.4.dist-info/RECORD
